{"ancient-lichen":"0.2026","lustrous-azure-moonstone":"600.8908","azure-moonstone-ring-(99)":"6.9991","stormy-azure-moonstone":"3.4158","solid-azure-moonstone":"0.5799","azure-moonstone":"0.5098","sparkling-azure-moonstone":"0.34","balanced-nightseye":"18.9974","balanced-shadow-draenite":"0.9884","runed-blood-garnet":"8.9","delicate-blood-garnet":"4.9995","bright-blood-garnet":"4.4989","bold-blood-garnet":"4.38","teardrop-blood-garnet":"4.2","blood-garnet":"2.32","bold-living-ruby":"60.7999","bracing-earthstorm-diamond":"79.8998","bright-living-ruby":"57.5","brilliant-golden-draenite":"2.3795","chaotic-skyfire-diamond":"116.6965","smooth-dawnstone":"14.8","rigid-dawnstone":"11.949","great-dawnstone":"11.8951","brilliant-dawnstone":"10.8977","mystic-dawnstone":"10.4997","gleaming-dawnstone":"9.5219","thick-dawnstone":"7.8993","dawnstone":"7.45","brutal-earthstorm-diamond":"150.0927","dazzling-deep-peridot":"0.9993","dazzling-talasite":"3.98","enduring-deep-peridot":"1.8397","deep-peridot":"0.4999","jagged-deep-peridot":"0.39","radiant-deep-peridot":"0.34","delicate-living-ruby":"60.5999","recipe:-destruction-potion":"645.9996","destruction-potion":"5.6996","destructive-skyfire-diamond":"71.9499","tenacious-earthstorm-diamond":"155.7499","insightful-earthstorm-diamond":"89.9999","powerful-earthstorm-diamond":"89.9795","relentless-earthstorm-diamond":"87.6995","earthstorm-diamond":"75.4999","enduring-talasite":"8.649","enigmatic-skyfire-diamond":"119.98","eternium-ore":"0.6997","fel-iron-ore":"0.5098","fel-lotus":"6.25","felsteel-bar":"9.08","veiled-flame-spessarite":"2.86","luminous-flame-spessarite":"1.4994","potent-flame-spessarite":"0.74","wicked-flame-spessarite":"0.4998","glinting-flame-spessarite":"0.49","inscribed-flame-spessarite":"0.4099","flame-spessarite":"0.2594","flashing-living-ruby":"55.8997","gleaming-golden-draenite":"3.9599","glinting-noble-topaz":"16.9436","glowing-shadow-draenite":"1.8","golden-draenite-ring-(93)":"7.9494","thick-golden-draenite":"5.0499","great-golden-draenite":"2.3998","rigid-golden-draenite":"0.9896","golden-draenite":"0.9699","smooth-golden-draenite":"0.65","recipe:-haste-potion":"729","haste-potion":"7.35","recipe:-heroic-potion":"12.7998","heroic-potion":"3.7999","infused-nightseye":"19.6491","infused-shadow-draenite":"0.4998","inscribed-noble-topaz":"21.9998","ironshield-potion":"2.84","jagged-talasite":"4.56","living-ruby-pendant-(113)":"99.9998","teardrop-living-ruby":"57.2999","subtle-living-ruby":"55.7992","runed-living-ruby":"55.7692","living-ruby":"49.0799","luminous-noble-topaz":"16.5999","lustrous-star-of-elune":"5","mote-of-earth":"0.55","mystical-skyfire-diamond":"102.4999","nightmare-vine":"2.4","sovereign-nightseye":"14.8983","royal-nightseye":"13.5499","shifting-nightseye":"11.5999","glowing-nightseye":"9.8998","nightseye":"6.1","potent-noble-topaz":"23.5999","veiled-noble-topaz":"19.8498","wicked-noble-topaz":"17.5476","noble-topaz":"9.7","primal-air":"10.3995","primal-earth":"4.4","primal-fire":"15.0999","primal-mana":"10.95","primal-might":"69.6","primal-water":"13.25","radiant-talasite":"4.3","royal-shadow-draenite":"1.359","shadow-draenite":"0.5599","shifting-shadow-draenite":"0.4896","sovereign-shadow-draenite":"0.33","swift-skyfire-diamond":"119.9799","skyfire-diamond":"93.8998","thundering-skyfire-diamond":"85.9982","solid-star-of-elune":"5.4491","sparkling-star-of-elune":"3.77","stormy-star-of-elune":"10.9492","star-of-elune":"3.26","steady-talasite":"6.8","swiftness-potion":"3.1798","recipe:-swiftness-potion":"1.34","swiftthistle":"2","talasite":"3","terocone":"2.9"}